README.md
setup.cfg
setup.py
faceitize/__init__.py
faceitize/debug.py
faceitize/lib.py
faceitize.egg-info/PKG-INFO
faceitize.egg-info/SOURCES.txt
faceitize.egg-info/dependency_links.txt
faceitize.egg-info/requires.txt
faceitize.egg-info/top_level.txt