Metadata-Version: 1.1
Name: faceitize
Version: 0.1.1
Summary: The incredible human to human face swapping package
Home-page: https://github.com/mattmatters/faceitize
Author: Matt Lewis
Author-email: domattthings@gmail.com
License: MIT
Download-URL: https://github.com/mattmatters/faceitize/archive/0.1.1.tar.gz
Platform: UNKNOWN
